LICENSE
README.md
setup.py
makit/orm/__init__.py
makit/orm/base.py
makit/orm/cache.py
makit/orm/connection.py
makit/orm/errors.py
makit/orm/expr.py
makit/orm/fields.py
makit/orm/filters.py
makit/orm/functions.py
makit/orm/migrate.py
makit/orm/model.py
makit/orm/query.py
makit/orm/utils.py
makit/orm/db/__init__.py
makit/orm/db/mysql.py
makit/orm/tests/__init__.py
makit/orm/tests/models.py
makit/orm/tests/preload_test.py
makit/orm/tests/select_test.py
makit/orm/tests/test_all.py
makitdone_orm.egg-info/PKG-INFO
makitdone_orm.egg-info/SOURCES.txt
makitdone_orm.egg-info/dependency_links.txt
makitdone_orm.egg-info/requires.txt
makitdone_orm.egg-info/top_level.txt